worin/__init__.py
worin/model.hdf5
worin/preproc.py
worin/tag.py
worin-0.1.0.dist-info/METADATA
worin-0.1.0.dist-info/RECORD
worin-0.1.0.dist-info/WHEEL
worin-0.1.0.dist-info/top_level.txt
